odoo10_addon_account_analytic_required-10.0.1.1.0-py2.7-nspkg.pth
odoo/addons/account_analytic_required/README.rst
odoo/addons/account_analytic_required/__init__.py
odoo/addons/account_analytic_required/__manifest__.py
odoo/addons/account_analytic_required/i18n/account_analytic_required.pot
odoo/addons/account_analytic_required/i18n/ar.po
odoo/addons/account_analytic_required/i18n/ca.po
odoo/addons/account_analytic_required/i18n/es.po
odoo/addons/account_analytic_required/i18n/fr.po
odoo/addons/account_analytic_required/i18n/hr_HR.po
odoo/addons/account_analytic_required/i18n/nl.po
odoo/addons/account_analytic_required/i18n/pt_BR.po
odoo/addons/account_analytic_required/models/__init__.py
odoo/addons/account_analytic_required/models/account.py
odoo/addons/account_analytic_required/tests/__init__.py
odoo/addons/account_analytic_required/tests/test_account_analytic_required.py
odoo/addons/account_analytic_required/views/account.xml
odoo10_addon_account_analytic_required-10.0.1.1.0.dist-info/DESCRIPTION.rst
odoo10_addon_account_analytic_required-10.0.1.1.0.dist-info/METADATA
odoo10_addon_account_analytic_required-10.0.1.1.0.dist-info/RECORD
odoo10_addon_account_analytic_required-10.0.1.1.0.dist-info/WHEEL
odoo10_addon_account_analytic_required-10.0.1.1.0.dist-info/metadata.json
odoo10_addon_account_analytic_required-10.0.1.1.0.dist-info/namespace_packages.txt
odoo10_addon_account_analytic_required-10.0.1.1.0.dist-info/top_level.txt
